traffic_light_controller.v
module traffic_light_controller (
    input clk,
    input rst,
    output reg [1:0] ns_light,
    output reg [1:0] ew_light,
    output reg [1:0] sn_light,
    output reg [1:0] we_light
);

parameter RED = 2'b00, GREEN = 2'b01, YELLOW = 2'b10;

// State encoding
parameter NS_GREEN = 3'd0,
          NS_YELLOW = 3'd1,
          EW_GREEN = 3'd2,
          EW_YELLOW = 3'd3,
          SN_GREEN = 3'd4,
          SN_YELLOW = 3'd5,
          WE_GREEN = 3'd6,
          WE_YELLOW = 3'd7;

reg [2:0] state, next_state;
reg [4:0] timer;

parameter GREEN_TIME = 10;
parameter YELLOW_TIME = 3;

always @(posedge clk or posedge rst) begin
    if (rst) begin
        state <= NS_GREEN;
        timer <= GREEN_TIME;
    end else if (timer == 0) begin
        state <= next_state;
        if (next_state == NS_YELLOW || next_state == EW_YELLOW ||
            next_state == SN_YELLOW || next_state == WE_YELLOW)
            timer <= YELLOW_TIME;
        else
            timer <= GREEN_TIME;
    end else begin
        timer <= timer - 1;
    end
end

always @(*) begin
    case (state)
        NS_GREEN:   next_state = NS_YELLOW;
        NS_YELLOW:  next_state = EW_GREEN;
        EW_GREEN:   next_state = EW_YELLOW;
        EW_YELLOW:  next_state = SN_GREEN;
        SN_GREEN:   next_state = SN_YELLOW;
        SN_YELLOW:  next_state = WE_GREEN;
        WE_GREEN:   next_state = WE_YELLOW;
        WE_YELLOW:  next_state = NS_GREEN;
        default:    next_state = NS_GREEN;
    endcase
end

always @(*) begin
    ns_light = RED;
    ew_light = RED;
    sn_light = RED;
    we_light = RED;

    case (state)
        NS_GREEN:   ns_light = GREEN;
        NS_YELLOW:  ns_light = YELLOW;
        EW_GREEN:   ew_light = GREEN;
        EW_YELLOW:  ew_light = YELLOW;
        SN_GREEN:   sn_light = GREEN;
        SN_YELLOW:  sn_light = YELLOW;
        WE_GREEN:   we_light = GREEN;
        WE_YELLOW:  we_light = YELLOW;
    endcase
end

endmodule

traffic_light_tb.v
`timescale 1ns/1ps
module traffic_light_tb;
  reg clk = 0;
  reg rst;
  wire [1:0] ns_light, ew_light, sn_light, we_light;

  traffic_light_controller dut (
    .clk(clk),
    .rst(rst),
    .ns_light(ns_light),
    .ew_light(ew_light),
    .sn_light(sn_light),
    .we_light(we_light)
  );

  always #5 clk = ~clk; // 10ns clock period (100MHz)

  initial begin
    $dumpfile("dump.vcd");
    $dumpvars(0, traffic_light_tb);

    rst = 1; #20;
    rst = 0;

    #1000;
    $finish;
  end
endmodule

dump.vcd
$date
	Tue Jun 17 00:59:59 2025
$end
$version
	Icarus Verilog
$end
$timescale
	1ps
$end
$scope module traffic_light_tb $end
$var wire 2 ! we_light [1:0] $end
$var wire 2 " sn_light [1:0] $end
$var wire 2 # ns_light [1:0] $end
$var wire 2 $ ew_light [1:0] $end
$var reg 1 % clk $end
$var reg 1 & rst $end
$scope module dut $end
$var wire 1 % clk $end
$var wire 1 & rst $end
$var parameter 3 ' EW_GREEN $end
$var parameter 3 ( EW_YELLOW $end
$var parameter 2 ) GREEN $end
$var parameter 32 * GREEN_TIME $end
$var parameter 3 + NS_GREEN $end
$var parameter 3 , NS_YELLOW $end
$var parameter 2 - RED $end
$var parameter 3 . SN_GREEN $end
$var parameter 3 / SN_YELLOW $end
$var parameter 3 0 WE_GREEN $end
$var parameter 3 1 WE_YELLOW $end
$var parameter 2 2 YELLOW $end
$var parameter 32 3 YELLOW_TIME $end
$var reg 2 4 ew_light [1:0] $end
$var reg 3 5 next_state [2:0] $end
$var reg 2 6 ns_light [1:0] $end
$var reg 2 7 sn_light [1:0] $end
$var reg 3 8 state [2:0] $end
$var reg 5 9 timer [4:0] $end
$var reg 2 : we_light [1:0] $end
$upscope $end
$upscope $end
$enddefinitions $end
$comment Show the parameter values. $end
$dumpall
b11 3
b10 2
b111 1
b110 0
b101 /
b100 .
b0 -
b1 ,
b0 +
b1010 *
b1 )
b11 (
b10 '
$end
#0
$dumpvars
b0 :
b1010 9
b0 8
b0 7
b1 6
b1 5
b0 4
1&
0%
b0 $
b1 #
b0 "
b0 !
$end
#5000
1%
#10000
0%
#15000
1%
#20000
0%
0&
#25000
b1001 9
1%
#30000
0%
#35000
b1000 9
1%
#40000
0%
#45000
b111 9
1%
#50000
0%
#55000
b110 9
1%
#60000
0%
#65000
b101 9
1%
#70000
0%
#75000
b100 9
1%
#80000
0%
#85000
b11 9
1%
#90000
0%
#95000
b10 9
1%
#100000
0%
#105000
b1 9
1%
#110000
0%
#115000
b0 9
1%
#120000
0%
#125000
b10 5
b10 #
b10 6
b11 9
b1 8
1%
#130000
0%
#135000
b10 9
1%
#140000
0%
#145000
b1 9
1%
#150000
0%
#155000
b0 9
1%
#160000
0%
#165000
b1 $
b1 4
b0 #
b0 6
b11 5
b1010 9
b10 8
1%
#170000
0%
#175000
b1001 9
1%
#180000
0%
#185000
b1000 9
1%
#190000
0%
#195000
b111 9
1%
#200000
0%
#205000
b110 9
1%
#210000
0%
#215000
b101 9
1%
#220000
0%
#225000
b100 9
1%
#230000
0%
#235000
b11 9
1%
#240000
0%
#245000
b10 9
1%
#250000
0%
#255000
b1 9
1%
#260000
0%
#265000
b0 9
1%
#270000
0%
#275000
b100 5
b10 $
b10 4
b11 9
b11 8
1%
#280000
0%
#285000
b10 9
1%
#290000
0%
#295000
b1 9
1%
#300000
0%
#305000
b0 9
1%
#310000
0%
#315000
b1 "
b1 7
b0 $
b0 4
b101 5
b1010 9
b100 8
1%
#320000
0%
#325000
b1001 9
1%
#330000
0%
#335000
b1000 9
1%
#340000
0%
#345000
b111 9
1%
#350000
0%
#355000
b110 9
1%
#360000
0%
#365000
b101 9
1%
#370000
0%
#375000
b100 9
1%
#380000
0%
#385000
b11 9
1%
#390000
0%
#395000
b10 9
1%
#400000
0%
#405000
b1 9
1%
#410000
0%
#415000
b0 9
1%
#420000
0%
#425000
b110 5
b10 "
b10 7
b11 9
b101 8
1%
#430000
0%
#435000
b10 9
1%
#440000
0%
#445000
b1 9
1%
#450000
0%
#455000
b0 9
1%
#460000
0%
#465000
b1 !
b1 :
b0 "
b0 7
b111 5
b1010 9
b110 8
1%
#470000
0%
#475000
b1001 9
1%
#480000
0%
#485000
b1000 9
1%
#490000
0%
#495000
b111 9
1%
#500000
0%
#505000
b110 9
1%
#510000
0%
#515000
b101 9
1%
#520000
0%
#525000
b100 9
1%
#530000
0%
#535000
b11 9
1%
#540000
0%
#545000
b10 9
1%
#550000
0%
#555000
b1 9
1%
#560000
0%
#565000
b0 9
1%
#570000
0%
#575000
b0 5
b10 !
b10 :
b11 9
b111 8
1%
#580000
0%
#585000
b10 9
1%
#590000
0%
#595000
b1 9
1%
#600000
0%
#605000
b0 9
1%
#610000
0%
#615000
b1 #
b1 6
b0 !
b0 :
b1 5
b1010 9
b0 8
1%
#620000
0%
#625000
b1001 9
1%
#630000
0%
#635000
b1000 9
1%
#640000
0%
#645000
b111 9
1%
#650000
0%
#655000
b110 9
1%
#660000
0%
#665000
b101 9
1%
#670000
0%
#675000
b100 9
1%
#680000
0%
#685000
b11 9
1%
#690000
0%
#695000
b10 9
1%
#700000
0%
#705000
b1 9
1%
#710000
0%
#715000
b0 9
1%
#720000
0%
#725000
b10 5
b10 #
b10 6
b11 9
b1 8
1%
#730000
0%
#735000
b10 9
1%
#740000
0%
#745000
b1 9
1%
#750000
0%
#755000
b0 9
1%
#760000
0%
#765000
b1 $
b1 4
b0 #
b0 6
b11 5
b1010 9
b10 8
1%
#770000
0%
#775000
b1001 9
1%
#780000
0%
#785000
b1000 9
1%
#790000
0%
#795000
b111 9
1%
#800000
0%
#805000
b110 9
1%
#810000
0%
#815000
b101 9
1%
#820000
0%
#825000
b100 9
1%
#830000
0%
#835000
b11 9
1%
#840000
0%
#845000
b10 9
1%
#850000
0%
#855000
b1 9
1%
#860000
0%
#865000
b0 9
1%
#870000
0%
#875000
b100 5
b10 $
b10 4
b11 9
b11 8
1%
#880000
0%
#885000
b10 9
1%
#890000
0%
#895000
b1 9
1%
#900000
0%
#905000
b0 9
1%
#910000
0%
#915000
b1 "
b1 7
b0 $
b0 4
b101 5
b1010 9
b100 8
1%
#920000
0%
#925000
b1001 9
1%
#930000
0%
#935000
b1000 9
1%
#940000
0%
#945000
b111 9
1%
#950000
0%
#955000
b110 9
1%
#960000
0%
#965000
b101 9
1%
#970000
0%
#975000
b100 9
1%
#980000
0%
#985000
b11 9
1%
#990000
0%
#995000
b10 9
1%
#1000000
0%
#1005000
b1 9
1%
#1010000
0%
#1015000
b0 9
1%
